oasis_stat/__init__.py
oasis_stat/oasis_stat.py
oasis_stat-1.1.2.dist-info/LICENSE
oasis_stat-1.1.2.dist-info/METADATA
oasis_stat-1.1.2.dist-info/WHEEL
oasis_stat-1.1.2.dist-info/top_level.txt
oasis_stat-1.1.2.dist-info/RECORD
