Metadata-Version: 2.1
Name: oasis_stat
Version: 1.1.2
Summary: OASIS statistical test for interpretable analysis of contingency tables.
Author-email: Tavor Z Baharav <tavorb@mit.edu>
Maintainer-email: Tavor Z Baharav <tavorb@mit.edu>
License: MIT license
Project-URL: bugs, https://github.com/tavorb/oasis_stat/issues
Project-URL: changelog, https://github.com/tavorb/oasis_stat/blob/master/changelog.md
Project-URL: homepage, https://github.com/tavorb/oasis_stat
License-File: LICENSE
Provides-Extra: dev
Requires-Dist: coverage ; extra == 'dev'
Requires-Dist: mypy ; extra == 'dev'
Requires-Dist: pytest ; extra == 'dev'
Requires-Dist: ruff ; extra == 'dev'
